[{"id":1,"name":"error: Field 'shakil' not found","Born":"error: invalid date \"\"","gender":"Genderqueer","img":"http://dummyimage.com/223x187.bmp/cc0000/ffffff","Role":"Fitness","salery":null},
{"id":2,"name":"error: Field 'hajl' not found","Born":"error: invalid date \"\"","gender":"Agender","img":"http://dummyimage.com/152x105.jpg/dddddd/000000","Role":"PPDS","salery":null},
{"id":3,"name":"error: Field 'hajl' not found","Born":"error: invalid date \"\"","gender":"Male","img":"http://dummyimage.com/161x145.png/cc0000/ffffff","Role":"NSN","salery":null},
{"id":4,"name":"error: Field 'hajl' not found","Born":"error: invalid date \"\"","gender":"Agender","img":"http://dummyimage.com/130x242.png/dddddd/000000","Role":"IO","salery":null},
{"id":5,"name":"error: Field 'hajl' not found","Born":"error: invalid date \"\"","gender":"Genderqueer","img":"http://dummyimage.com/133x167.jpg/ff4444/ffffff","Role":"Outsourcing Management","salery":null},
{"id":6,"name":"error: Field 'hajl' not found","Born":"error: invalid date \"\"","gender":"Non-binary","img":"http://dummyimage.com/101x155.png/5fa2dd/ffffff","Role":"Automation","salery":null},
{"id":7,"name":"error: Field 'hajl' not found","Born":"error: invalid date \"\"","gender":"Polygender","img":"http://dummyimage.com/180x159.jpg/cc0000/ffffff","Role":"Gynecology","salery":null},
{"id":8,"name":"error: Field 'hajl' not found","Born":"error: invalid date \"\"","gender":"Bigender","img":"http://dummyimage.com/166x146.jpg/5fa2dd/ffffff","Role":"Graduate Recruitment","salery":null},
{"id":9,"name":"error: Field 'hajl' not found","Born":"error: invalid date \"\"","gender":"Female","img":"http://dummyimage.com/129x116.jpg/dddddd/000000","Role":"MSS","salery":null},
{"id":10,"name":"error: Field 'hajl' not found","Born":"error: invalid date \"\"","gender":"Non-binary","img":"http://dummyimage.com/136x186.bmp/ff4444/ffffff","Role":"Awk","salery":null},
{"id":11,"name":"error: Field 'hajl' not found","Born":"error: invalid date \"\"","gender":"Genderfluid","img":"http://dummyimage.com/130x209.jpg/5fa2dd/ffffff","Role":"Guardianship","salery":null},
{"id":12,"name":"error: Field 'hajl' not found","Born":"error: invalid date \"\"","gender":"Female","img":"http://dummyimage.com/103x177.png/ff4444/ffffff","Role":"CBCP","salery":null},
{"id":13,"name":"error: Field 'hajl' not found","Born":"error: invalid date \"\"","gender":"Genderfluid","img":"http://dummyimage.com/211x115.bmp/ff4444/ffffff","Role":"MD-11","salery":null},
{"id":14,"name":"error: Field 'hajl' not found","Born":"error: invalid date \"\"","gender":"Male","img":"http://dummyimage.com/184x191.png/dddddd/000000","Role":"Billing Systems","salery":null},
{"id":15,"name":"error: Field 'hajl' not found","Born":"error: invalid date \"\"","gender":"Genderqueer","img":"http://dummyimage.com/150x183.bmp/ff4444/ffffff","Role":"Customer Acquisition","salery":null}]